{"APT 28": [1, 0, 0, 0, 0, 0, 0, 0, 0, 0, 0], "Gorgon Group": [0, 1, 0, 0, 0, 0, 0, 0, 0, 0, 0], "Equation Group": [0, 0, 1, 0, 0, 0, 0, 0, 0, 0, 0], "APT 10": [0, 0, 0, 1, 0, 0, 0, 0, 0, 0, 0], "APT 1": [0, 0, 0, 0, 1, 0, 0, 0, 0, 0, 0], "APT 29": [0, 0, 0, 0, 0, 1, 0, 0, 0, 0, 0], "Winnti": [0, 0, 0, 0, 0, 0, 1, 0, 0, 0, 0], "APT 21": [0, 0, 0, 0, 0, 0, 0, 1, 0, 0, 0], "Dark Hotel": [0, 0, 0, 0, 0, 0, 0, 0, 1, 0, 0], "APT 19": [0, 0, 0, 0, 0, 0, 0, 0, 0, 1, 0], "APT 30": [0, 0, 0, 0, 0, 0, 0, 0, 0, 0, 1]}